wexample_helpers_git-0.0.96.dist-info/METADATA
wexample_helpers_git-0.0.96.dist-info/WHEEL
wexample_helpers_git-0.0.96.dist-info/entry_points.txt
wexample_helpers_git/__init__.py
wexample_helpers_git/__pycache__/__init__.py
wexample_helpers_git/const/__init__.py
wexample_helpers_git/const/common.py
wexample_helpers_git/helpers/__init__.py
wexample_helpers_git/helpers/__pycache__/__init__.py
wexample_helpers_git/helpers/git.py
wexample_helpers_git/py.typed
wexample_helpers_git-0.0.96.dist-info/RECORD
